lantrane/__init__.py
lantrane/data.py
lantrane/eventmanager.py
lantrane/lantrane.py
lantrane/trane.py
lantrane-0.0.5.dist-info/LICENSE.md
lantrane-0.0.5.dist-info/METADATA
lantrane-0.0.5.dist-info/WHEEL
lantrane-0.0.5.dist-info/top_level.txt
lantrane-0.0.5.dist-info/RECORD
