Metadata-Version: 2.1
Name: lantrane
Version: 0.0.5
Summary: Python package for interacting with Trane thermostats locally.
Home-page: https://github.com/MoralCode/lantrane
Author: Adrian Edwards
Author-email: adrian@adriancedwards.com
License: UNKNOWN
Platform: UNKNOWN
Classifier: Programming Language :: Python :: 3
Classifier: Operating System :: OS Independent
Requires-Python: >=3
License-File: LICENSE.md
